__init__.py
v1/__init__.py
v1/client.py
v1/example.py
v1/test_client.py
agntcy_dir_sdk-0.1.10.dist-info/METADATA
agntcy_dir_sdk-0.1.10.dist-info/WHEEL
agntcy_dir_sdk-0.1.10.dist-info/top_level.txt
agntcy_dir_sdk-0.1.10.dist-info/RECORD
