Metadata-Version: 2.4
Name: agntcy-dir-sdk
Version: 0.1.10
Summary: Directory client SDK
Requires-Python: >=3.9
Requires-Dist: agntcy-dir-grpc-python==1.74.0.1.20250730140857+ac127ee206f2
